mp4analyzer/__init__.py
mp4analyzer/_version.py
mp4analyzer/cli.py
mp4analyzer/movieinfo.py
mp4analyzer/parser.py
mp4analyzer/utils.py
mp4analyzer/boxes/__init__.py
mp4analyzer/boxes/ac4.py
mp4analyzer/boxes/av01.py
mp4analyzer/boxes/av1c.py
mp4analyzer/boxes/avc1.py
mp4analyzer/boxes/avcc.py
mp4analyzer/boxes/base.py
mp4analyzer/boxes/btrt.py
mp4analyzer/boxes/chpl.py
mp4analyzer/boxes/colr.py
mp4analyzer/boxes/ctts.py
mp4analyzer/boxes/dac4.py
mp4analyzer/boxes/data.py
mp4analyzer/boxes/dinf.py
mp4analyzer/boxes/dref.py
mp4analyzer/boxes/edts.py
mp4analyzer/boxes/elst.py
mp4analyzer/boxes/esds.py
mp4analyzer/boxes/fiel.py
mp4analyzer/boxes/free.py
mp4analyzer/boxes/ftyp.py
mp4analyzer/boxes/gmhd.py
mp4analyzer/boxes/hdlr.py
mp4analyzer/boxes/hev1.py
mp4analyzer/boxes/hvcc.py
mp4analyzer/boxes/ilst.py
mp4analyzer/boxes/iods.py
mp4analyzer/boxes/mdat.py
mp4analyzer/boxes/mdhd.py
mp4analyzer/boxes/mdia.py
mp4analyzer/boxes/mehd.py
mp4analyzer/boxes/meta.py
mp4analyzer/boxes/mfhd.py
mp4analyzer/boxes/mfra.py
mp4analyzer/boxes/mfro.py
mp4analyzer/boxes/minf.py
mp4analyzer/boxes/moof.py
mp4analyzer/boxes/moov.py
mp4analyzer/boxes/mp4a.py
mp4analyzer/boxes/mvex.py
mp4analyzer/boxes/mvhd.py
mp4analyzer/boxes/pasp.py
mp4analyzer/boxes/sbgp.py
mp4analyzer/boxes/sdtp.py
mp4analyzer/boxes/sgpd.py
mp4analyzer/boxes/smhd.py
mp4analyzer/boxes/stbl.py
mp4analyzer/boxes/stco.py
mp4analyzer/boxes/stsc.py
mp4analyzer/boxes/stsd.py
mp4analyzer/boxes/stss.py
mp4analyzer/boxes/stsz.py
mp4analyzer/boxes/stts.py
mp4analyzer/boxes/text.py
mp4analyzer/boxes/tfdt.py
mp4analyzer/boxes/tfhd.py
mp4analyzer/boxes/tfra.py
mp4analyzer/boxes/tkhd.py
mp4analyzer/boxes/traf.py
mp4analyzer/boxes/trak.py
mp4analyzer/boxes/tref.py
mp4analyzer/boxes/trex.py
mp4analyzer/boxes/trun.py
mp4analyzer/boxes/udta.py
mp4analyzer/boxes/url_.py
mp4analyzer/boxes/vmhd.py
mp4analyzer-1.1.6.dist-info/licenses/LICENSE
mp4analyzer-1.1.6.dist-info/METADATA
mp4analyzer-1.1.6.dist-info/WHEEL
mp4analyzer-1.1.6.dist-info/entry_points.txt
mp4analyzer-1.1.6.dist-info/top_level.txt
mp4analyzer-1.1.6.dist-info/RECORD
