Metadata-Version: 2.4
Name: mp4analyzer
Version: 1.1.6
Summary: Lightweight MP4 box analyzer
Author-email: Andrew Xin <andrewx@bu.edu>
License-Expression: MIT
Classifier: Programming Language :: Python :: 3
Classifier: Operating System :: OS Independent
Classifier: Topic :: Multimedia :: Video
Requires-Python: >=3.11
License-File: LICENSE
Provides-Extra: gui
Requires-Dist: PyQt6>=6.9; extra == "gui"
Requires-Dist: pillow>=11.3; extra == "gui"
Requires-Dist: psutil>=5.9; extra == "gui"
Provides-Extra: dev
Requires-Dist: ruff>=0.12; extra == "dev"
Requires-Dist: black>=25.1; extra == "dev"
Requires-Dist: pytest>=8.4; extra == "dev"
Requires-Dist: pyinstaller>=6.15; extra == "dev"
Requires-Dist: PyQt6>=6.9; extra == "dev"
Requires-Dist: pillow>=11.3; extra == "dev"
Requires-Dist: psutil>=5.9; extra == "dev"
Dynamic: license-file
